pyomo/__init__.py
pyomo/future.py
pyomo/_archive/__init__.py
pyomo/_archive/chull.py
pyomo/_archive/component_map.py
pyomo/_archive/component_set.py
pyomo/_archive/current.py
pyomo/_archive/plugin.py
pyomo/_archive/rangeset.py
pyomo/_archive/register_numpy_types.py
pyomo/_archive/sets.py
pyomo/_archive/template_expr.py
pyomo/common/__init__.py
pyomo/common/_command.py
pyomo/common/_common.py
pyomo/common/autoslots.py
pyomo/common/backports.py
pyomo/common/cmake_builder.py
pyomo/common/config.py
pyomo/common/dependencies.py
pyomo/common/deprecation.py
pyomo/common/download.py
pyomo/common/enums.py
pyomo/common/env.py
pyomo/common/envvar.py
pyomo/common/errors.py
pyomo/common/extensions.py
pyomo/common/factory.py
pyomo/common/fileutils.py
pyomo/common/flags.py
pyomo/common/formatting.py
pyomo/common/gc_manager.py
pyomo/common/gsl.py
pyomo/common/log.py
pyomo/common/modeling.py
pyomo/common/multithread.py
pyomo/common/numeric_types.py
pyomo/common/plugin_base.py
pyomo/common/plugins.py
pyomo/common/pyomo_typing.py
pyomo/common/shutdown.py
pyomo/common/sorting.py
pyomo/common/tee.py
pyomo/common/tempfiles.py
pyomo/common/timing.py
pyomo/common/unittest.py
pyomo/common/collections/__init__.py
pyomo/common/collections/_hasher.py
pyomo/common/collections/bunch.py
pyomo/common/collections/component_map.py
pyomo/common/collections/component_set.py
pyomo/common/collections/orderedset.py
pyomo/common/tests/__init__.py
pyomo/common/tests/config_plugin.py
pyomo/common/tests/dep_mod.py
pyomo/common/tests/dep_mod_except.py
pyomo/common/tests/deps.py
pyomo/common/tests/import_ex.py
pyomo/common/tests/mod.py
pyomo/common/tests/moved.py
pyomo/common/tests/relo_mod.py
pyomo/common/tests/relo_mod_new.py
pyomo/common/tests/relocated.py
pyomo/common/tests/test_bunch.py
pyomo/common/tests/test_component_map.py
pyomo/common/tests/test_config.py
pyomo/common/tests/test_dependencies.py
pyomo/common/tests/test_deprecated.py
pyomo/common/tests/test_download.py
pyomo/common/tests/test_enums.py
pyomo-6.9.5.dist-info/licenses/LICENSE.md
pyomo-6.9.5.dist-info/METADATA
pyomo-6.9.5.dist-info/WHEEL
pyomo-6.9.5.dist-info/entry_points.txt
pyomo-6.9.5.dist-info/top_level.txt
pyomo-6.9.5.dist-info/RECORD
