Metadata-Version: 2.4
Name: pyomo
Version: 6.9.5
Summary: The Pyomo optimization modeling framework
Author-email: Pyomo Development Team <pyomo-developers@googlegroups.com>
License-Expression: BSD-3-Clause
Project-URL: Homepage, https://www.pyomo.org
Project-URL: Documentation, https://pyomo.readthedocs.io/en/stable/
Project-URL: Source, https://github.com/Pyomo/pyomo
Keywords: optimization
Classifier: Development Status :: 5 - Production/Stable
Classifier: Intended Audience :: End Users/Desktop
Classifier: Intended Audience :: Science/Research
Classifier: Natural Language :: English
Classifier: Operating System :: MacOS
Classifier: Operating System :: Microsoft :: Windows
Classifier: Operating System :: Unix
Classifier: Programming Language :: Python
Classifier: Programming Language :: Python :: 3
Classifier: Programming Language :: Python :: 3.9
Classifier: Programming Language :: Python :: 3.10
Classifier: Programming Language :: Python :: 3.11
Classifier: Programming Language :: Python :: 3.12
Classifier: Programming Language :: Python :: 3.13
Classifier: Programming Language :: Python :: 3.14
Classifier: Programming Language :: Python :: Implementation :: CPython
Classifier: Programming Language :: Python :: Implementation :: PyPy
Classifier: Topic :: Scientific/Engineering :: Mathematics
Classifier: Topic :: Software Development :: Libraries :: Python Modules
Requires-Python: >=3.9
License-File: LICENSE.md
Requires-Dist: ply
Provides-Extra: tests
Requires-Dist: coverage; extra == "tests"
Requires-Dist: parameterized; extra == "tests"
Requires-Dist: pybind11; extra == "tests"
Requires-Dist: pytest; extra == "tests"
Requires-Dist: pytest-parallel; extra == "tests"
Provides-Extra: docs
Requires-Dist: Sphinx!=8.2.0,>4; extra == "docs"
Requires-Dist: sphinx-copybutton; extra == "docs"
Requires-Dist: sphinx_rtd_theme>0.5; extra == "docs"
Requires-Dist: sphinxcontrib-jsmath; extra == "docs"
Requires-Dist: sphinxcontrib-napoleon; extra == "docs"
Requires-Dist: numpy; extra == "docs"
Requires-Dist: scipy; extra == "docs"
Provides-Extra: optional
Requires-Dist: dill; extra == "optional"
Requires-Dist: ipython; extra == "optional"
Requires-Dist: linear-tree; python_version < "3.14" and extra == "optional"
Requires-Dist: scikit-learn<1.7.0; (implementation_name != "pypy" and python_version < "3.14") and extra == "optional"
Requires-Dist: scikit-learn; (implementation_name != "pypy" and python_version >= "3.14") and extra == "optional"
Requires-Dist: matplotlib!=3.6.1,>=3.6.0; extra == "optional"
Requires-Dist: networkx; extra == "optional"
Requires-Dist: numpy; extra == "optional"
Requires-Dist: openpyxl; extra == "optional"
Requires-Dist: packaging; extra == "optional"
Requires-Dist: pint; implementation_name != "pypy" and extra == "optional"
Requires-Dist: plotly; extra == "optional"
Requires-Dist: python-louvain; extra == "optional"
Requires-Dist: pyyaml; extra == "optional"
Requires-Dist: qtconsole; extra == "optional"
Requires-Dist: scipy; extra == "optional"
Requires-Dist: sympy; extra == "optional"
Requires-Dist: xlrd; extra == "optional"
Requires-Dist: z3-solver; extra == "optional"
Requires-Dist: pywin32; platform_system == "Windows" and extra == "optional"
Requires-Dist: casadi; implementation_name != "pypy" and extra == "optional"
Requires-Dist: numdifftools; implementation_name != "pypy" and extra == "optional"
Requires-Dist: pandas; implementation_name != "pypy" and extra == "optional"
Requires-Dist: seaborn; implementation_name != "pypy" and extra == "optional"
Dynamic: license-file
Dynamic: provides-extra
Dynamic: requires-dist
